Plugthon/__init__.py
Plugthon/__version__.py
Plugthon/plugins/__init__.py
Plugthon/plugins/hello.py
Plugthon/plugins/timer.py
Plugthon-0.3.0.dist-info/LICENSE
Plugthon-0.3.0.dist-info/METADATA
Plugthon-0.3.0.dist-info/WHEEL
Plugthon-0.3.0.dist-info/top_level.txt
Plugthon-0.3.0.dist-info/RECORD
