Metadata-Version: 2.2
Name: Plugthon
Version: 0.3.0
Summary: Plugthon is a developer-friendly library for building modular and scalable Telegram bots.
Home-page: https://github.com/Plugthon/Plugthon
Author: iniridwanul
Author-email: iniridwanul@gmail.com
License: AGPL
Keywords: Plugthon,Python,Telethon,Telegram bots,Userbot,Telegram
Classifier: Programming Language :: Python :: 3
Classifier: Operating System :: OS Independent
Requires-Python: >=3.6
License-File: LICENSE
Requires-Dist: Telethon
Dynamic: author
Dynamic: author-email
Dynamic: classifier
Dynamic: description
Dynamic: description-content-type
Dynamic: home-page
Dynamic: keywords
Dynamic: license
Dynamic: requires-dist
Dynamic: requires-python
Dynamic: summary
